fmmpy_directory_compressor/__init__.py
fmmpy_directory_compressor/unix/fmmpy_directory_compressor.cpython-38-x86_64-linux-gnu.so
fmmpy_directory_compressor/win32/boost_filesystem-vc143-mt-x64-1_78.dll
fmmpy_directory_compressor/win32/bz2.dll
fmmpy_directory_compressor/win32/fmmpy_directory_compressor.cp310-win_amd64.pyd
fmmpy_directory_compressor/win32/fmmpy_directory_compressor.exp
fmmpy_directory_compressor/win32/fmmpy_directory_compressor.lib
fmmpy_directory_compressor/win32/python310.dll
fmmpy_directory_compressor/win32/zip.dll
fmmpy_directory_compressor/win32/zlib1.dll
fmmpy_directory_compressor-0.1.0.post2.dist-info/LICENSE
fmmpy_directory_compressor-0.1.0.post2.dist-info/METADATA
fmmpy_directory_compressor-0.1.0.post2.dist-info/WHEEL
fmmpy_directory_compressor-0.1.0.post2.dist-info/top_level.txt
fmmpy_directory_compressor-0.1.0.post2.dist-info/RECORD
