Metadata-Version: 2.1
Name: fmmpy-directory-compressor
Version: 0.1.0.post2
Summary: Compress a directory into a single .FSA file.
Home-page: https://github.com/w-kuipers/fmm-directory-compressor
Author: Wibo Kuipers
Author-email: w.kuipers@filmage.nl
License: UNKNOWN
Project-URL: Bug Tracker, https://github.com/w-kuipers/fmm-directory-compressor/issues
Platform: UNKNOWN
Classifier: Programming Language :: Python :: 3
Classifier: License :: OSI Approved :: GNU General Public License v3 (GPLv3)
Classifier: Operating System :: POSIX :: Linux
Classifier: Operating System :: Microsoft :: Windows
Requires-Python: >=3.8
License-File: LICENSE
